tscal/__init__.py
tscal/main.py
tscal/style.tcss
tscal-0.2.0.dist-info/METADATA
tscal-0.2.0.dist-info/WHEEL
tscal-0.2.0.dist-info/entry_points.txt
tscal-0.2.0.dist-info/licenses/LICENSE
tscal-0.2.0.dist-info/RECORD
